excelcy/.git/HEAD
excelcy/.git/config
excelcy/.git/description
excelcy/.git/hooks/applypatch-msg.sample
excelcy/.git/hooks/commit-msg.sample
excelcy/.git/hooks/post-update.sample
excelcy/.git/hooks/pre-applypatch.sample
excelcy/.git/hooks/pre-commit.sample
excelcy/.git/hooks/pre-push.sample
excelcy/.git/hooks/pre-rebase.sample
excelcy/.git/hooks/pre-receive.sample
excelcy/.git/hooks/prepare-commit-msg.sample
excelcy/.git/hooks/update.sample
excelcy/.git/info/exclude
excelcy/__init__.py
excelcy/cli.py
excelcy/errors.py
excelcy/excelcy.py
excelcy/pipe.py
excelcy/registry.py
excelcy/storage.py
excelcy/utils.py
excelcy-0.4.1.dist-info/LICENSE
excelcy-0.4.1.dist-info/WHEEL
excelcy-0.4.1.dist-info/METADATA
excelcy-0.4.1.dist-info/RECORD
