Metadata-Version: 2.1
Name: excelcy
Version: 0.4.1
Summary: Excel Integration with SpaCy. Includes, Entity training, Entity matcher pipe.
Home-page: https://github.com/kororo/excelcy
License: MIT
Keywords: spacy,spacy-pipeline,spacy-nlp,nlp,python,python3,entity,training,excel,xlsx,spacy-extensions
Author: kororo
Author-email: kororo@users.noreply.github.com
Requires-Python: >=3.6,<4.0
Classifier: License :: OSI Approved :: MIT License
Classifier: Programming Language :: Python :: 3
Classifier: Programming Language :: Python :: 3.6
Classifier: Programming Language :: Python :: 3.7
Classifier: Programming Language :: Python :: 3.8
Requires-Dist: attrs (>=20.1.0,<21.0.0)
Requires-Dist: pyexcel (>=0.6.4,<0.7.0)
Requires-Dist: pyexcel-xlsx (>=0.5.8,<0.6.0)
Requires-Dist: pytest (>=5.4.3,<6.0.0)
Requires-Dist: pytest-cov (>=2.0,<3.0)
Requires-Dist: pyyaml (>=5.3.1,<6.0.0)
Requires-Dist: spacy (>=2.3.2,<3.0.0)
Project-URL: Repository, https://github.com/kororo/excelcy
